Spartan/__init__.py
Spartan/spartan.py
Spartan/lib/__init__.py
Spartan/lib/nmap-services
Spartan/lib/objects.py
Spartan/lib/packet.py
Spartan/lib/port_scan.py
Spartan/lib/script_execute.py
Spartan/lib/helpers/__init__.py
Spartan/lib/helpers/cms_detector.py
Spartan/lib/helpers/helpers.py
fun/__init__.py
fun/ldap.py
fun/router.py
fun/test1.py
fun/walet.py
cyberspartan-0.1.1.dist-info/METADATA
cyberspartan-0.1.1.dist-info/WHEEL
cyberspartan-0.1.1.dist-info/entry_points.txt
cyberspartan-0.1.1.dist-info/top_level.txt
cyberspartan-0.1.1.dist-info/RECORD
