Metadata-Version: 2.1
Name: cyberspartan
Version: 0.1.1
Summary: TCP/IP port scanner written in python
Home-page: https://github.org/dannyx-hub/Spartan
Author: dannyx-hub
Author-email: daro322.dp@gmail.com
License: GPL-3.0 license
Requires-Dist: tabulate
Requires-Dist: art
